aiogaro/__init__.py
aiogaro/chargebox.py
aiogaro-0.0.4.dist-info/LICENSE
aiogaro-0.0.4.dist-info/METADATA
aiogaro-0.0.4.dist-info/WHEEL
aiogaro-0.0.4.dist-info/top_level.txt
aiogaro-0.0.4.dist-info/RECORD
