Metadata-Version: 2.1
Name: aiogaro
Version: 0.0.4
Summary: Library to access Garo Chargeboxes
Home-page: https://github.com/kaboing/aiogaro/
Author: Jonas Lincoln
Author-email: jonas@lincoln.se
License: MIT
Classifier: Intended Audience :: Developers
Classifier: License :: OSI Approved :: MIT License
Classifier: Programming Language :: Python
Classifier: Programming Language :: Python :: 3
Classifier: Programming Language :: Python :: 3.9
Classifier: Programming Language :: Python :: 3.10
Classifier: Operating System :: OS Independent
License-File: LICENSE
Requires-Dist: aiohttp
